detect_litter/__init__.py
detect_litter/main.py
detect_litter-0.0.1.dist-info/LICENSE
detect_litter-0.0.1.dist-info/METADATA
detect_litter-0.0.1.dist-info/WHEEL
detect_litter-0.0.1.dist-info/entry_points.txt
detect_litter-0.0.1.dist-info/top_level.txt
detect_litter-0.0.1.dist-info/RECORD
