Metadata-Version: 2.1
Name: detect-litter
Version: 0.0.1
Summary: Detect Git Litter
Home-page: https://github.com/tvuillemin/detect-litter
Author: Thibaut Vuillemin
Author-email: contact@thibautvuillemin.com
License: UNKNOWN
Platform: UNKNOWN
Classifier: Programming Language :: Python :: 3
Classifier: Operating System :: OS Independent
Requires-Python: >=3.6
